fastapi_lib/__init__.py
fastapi_lib/patterns/__init__.py
fastapi_lib/patterns/repository.py
fastapi_lib-25.6.2.dist-info/METADATA
fastapi_lib-25.6.2.dist-info/WHEEL
fastapi_lib-25.6.2.dist-info/top_level.txt
fastapi_lib-25.6.2.dist-info/RECORD
